aqt_connector/__init__.py
aqt_connector/__main__.py
aqt_connector/_arnica_app.py
aqt_connector/_data_types.py
aqt_connector/_sdk_config.py
aqt_connector/exceptions.py
aqt_connector/py.typed
aqt_connector/_application/__init__.py
aqt_connector/_application/authentication.py
aqt_connector/_application/cli.py
aqt_connector/_application/jobs.py
aqt_connector/_domain/__init__.py
aqt_connector/_domain/auth_service.py
aqt_connector/_domain/job_service.py
aqt_connector/_domain/oidc_service.py
aqt_connector/_infrastructure/__init__.py
aqt_connector/_infrastructure/access_token_verifier.py
aqt_connector/_infrastructure/arnica_adapter.py
aqt_connector/_infrastructure/auth0_adapter.py
aqt_connector/_infrastructure/token_repository.py
aqt_connector/models/__init__.py
aqt_connector/models/circuits.py
aqt_connector/models/operations.py
aqt_connector/models/resources.py
aqt_connector/models/arnica/jobs.py
aqt_connector/models/arnica/resources.py
aqt_connector/models/arnica/request_bodies/__init__.py
aqt_connector/models/arnica/request_bodies/jobs.py
aqt_connector/models/arnica/response_bodies/__init__.py
aqt_connector/models/arnica/response_bodies/jobs.py
aqt_connector/models/arnica/response_bodies/resources.py
aqt_connector/models/arnica/response_bodies/workspaces.py
aqt_connector-0.2.0.dist-info/METADATA
aqt_connector-0.2.0.dist-info/WHEEL
aqt_connector-0.2.0.dist-info/licenses/LICENSE
aqt_connector-0.2.0.dist-info/RECORD
