Metadata-Version: 2.4
Name: aqt-connector
Version: 0.2.0
Summary: Python connector for services provided by AQT
Project-URL: Changelog, https://github.com/alpine-quantum-technologies/aqt-connector/blob/main/CHANGELOG.md
Project-URL: Documentation, https://github.com/alpine-quantum-technologies/aqt-connector/blob/main/README.md
Project-URL: Homepage, https://www.aqt.eu/products/arnica/
Project-URL: Issues, https://github.com/alpine-quantum-technologies/aqt-connector/issues
Project-URL: Repository, https://github.com/alpine-quantum-technologies/aqt-connector
Author-email: Alpine Quantum Technologies GmbH <support.arnica@aqt.eu>
License-Expression: Apache-2.0
License-File: LICENSE
Keywords: AQT,Alpine Quantum Technologies GmbH,Arnica,Direct Access API,Quantum Computing
Classifier: Programming Language :: Python :: 3 :: Only
Classifier: Programming Language :: Python :: 3.9
Classifier: Programming Language :: Python :: 3.10
Classifier: Programming Language :: Python :: 3.11
Classifier: Programming Language :: Python :: 3.12
Classifier: Programming Language :: Python :: 3.13
Requires-Python: <3.14,>=3.9
Requires-Dist: auth0-python<5,>=4.7.2
Requires-Dist: httpx<1,>=0.27.2
Requires-Dist: pydantic<3,>=2.10
Requires-Dist: qrcode<9,>=8
Requires-Dist: tomli<3,>=2.1
Requires-Dist: typer<1,>=0.13
